imageops/__init__.py
imageops/filters.py
imageops/histogram.py
imageops/neighborhood_ops.py
imageops/point.py
imageops/utils.py
imageops_sribalajistr-0.1.0.dist-info/METADATA
imageops_sribalajistr-0.1.0.dist-info/WHEEL
imageops_sribalajistr-0.1.0.dist-info/top_level.txt
imageops_sribalajistr-0.1.0.dist-info/RECORD
