Metadata-Version: 2.4
Name: imageops_sribalajiSTR
Version: 0.1.0
Summary: Custom image processing operators: point, filter, histogram, etc.
Author: SRI BALAJI P _ STR
Author-email: sribalajipurushothaman@gmail.com
Classifier: Programming Language :: Python :: 3
Classifier: Operating System :: OS Independent
Requires-Python: >=3.6
Requires-Dist: opencv-python
Requires-Dist: numpy
Requires-Dist: matplotlib
Dynamic: author
Dynamic: author-email
Dynamic: classifier
Dynamic: requires-dist
Dynamic: requires-python
Dynamic: summary
